fibermat/__init__.py
fibermat/mat.py
fibermat/mesh.py
fibermat/net.py
fibermat/solver.py
fibermat/model/__init__.py
fibermat/model/shear.py
fibermat/model/timoshenko.py
fibermat/utils/__init__.py
fibermat/utils/interpolation.py
fibermat/utils/render.py
fibermat/utils/widgets.py
fibermat-1.0.12.dist-info/METADATA
fibermat-1.0.12.dist-info/WHEEL
fibermat-1.0.12.dist-info/licenses/LICENSE
fibermat-1.0.12.dist-info/RECORD
