Metadata-Version: 2.3
Name: fibermat
Version: 1.0.12
Summary: A mechanical solver to simulate fiber packing and perform statistical analysis.
Project-URL: Homepage, https://github.com/fmahe/fibermat
Project-URL: Documentation, https://fibermat.readthedocs.io/en/latest/
Project-URL: Issues, https://github.com/fmahe/fibermat/issues
Author-email: François Mahé <francois.mahe@ens-rennes.fr>
License-File: LICENSE
Keywords: Timoshenko,fiber,mat,mechanics,mesostructure,porous
Classifier: License :: OSI Approved :: MIT License
Classifier: Operating System :: OS Independent
Classifier: Programming Language :: Python :: 3
Requires-Python: >=3.8
Requires-Dist: ipython
Requires-Dist: ipywidgets
Requires-Dist: matplotlib
Requires-Dist: numpy
Requires-Dist: pandas
Requires-Dist: pyvista
Requires-Dist: scikit-learn
Requires-Dist: scipy
Requires-Dist: tqdm
